[
  {"lifeSpan": {
    "begin": "2010-01-15",
    "end": "",
    "ended": "false"
  }},
  {"lifeSpan": {
    "begin": "2010-02-15",
    "end": "",
    "ended": "false"
  }},
  {"lifeSpan": {
    "begin": "2010-03-15",
    "end": "",
    "ended": "false"
  }},
  {"lifeSpan": {
    "begin": "2010-04-15",
    "end": "",
    "ended": "false"
  }},
  {"lifeSpan": {
    "begin": "2010-05-15",
    "end": "",
    "ended": "false"
  }},
  {"lifeSpan": {
    "begin": "2010-06-15",
    "end": "",
    "ended": "false"
  }},
  {"lifeSpan": {
    "begin": "2010-07-15",
    "end": "",
    "ended": "false"
  }},
  {"lifeSpan": {
    "begin": "2010-08-15",
    "end": "",
    "ended": "false"
  }},
  {"lifeSpan": {
    "begin": "2010-09-15",
    "end": "",
    "ended": "false"
  }},
  {"lifeSpan": {
    "begin": "2010-10-15",
    "end": "",
    "ended": "false"
  }},
  {"lifeSpan": {
    "begin": "2010-11-15",
    "end": "",
    "ended": "false"
  }},
  {"lifeSpan": {
    "begin": "2010-12",
    "end": "",
    "ended": "false"
  }}
]